Workbook

Sheet Executive Dashboard
A4: CE-018 PROJECT CONTROLS ASSURANCE SCORECARD
A5: S2 - Current programme evidence missing | ISSUED FOR PROJECT MANAGER REVIEW (IFR) - NOT APPROVED | Report ID CE018-S2-DRR-REV3.1
A6: Rev 3.1 controlled correction of Rev 3.0 - assessment not rerun. Scores, route, control results, Clause 64.1 statuses, exposure and retained authority unchanged.
A9: PROJECT AND EVENT METADATA
A10: Project | B10: Westbridge Station Access and Enabling Works | D10: Project ID | E10: WSAE
A11: Client | B11: Westbridge Transit Authority | D11: Contractor | E11: Northstar Civil Engineering Ltd
A12: Interface organisation | B12: CityRail Operations | D12: Contract scenario | E12: NEC4 ECC demonstration - base process, no relevant Z-clause amendment configured
A13: Event | B13: CE-018 - Restricted access to the Platform 4 worksite | D13: Related early warning | E13: EW-006 - separate earlier warning concerning the same access issue
A14: Assessment data cut-off | B14: 2026-03-31 | D14: Evidence revision basis | E14: Source_Register.csv | SRC-001 | rev 3.0
A15: Decision owner | B15: Elena Brooks - NEC4 Project Manager | D15: Control owner | E15: Sofia Khan - Project Controls Lead
A16: Report status and revision | B16: ISSUED FOR PROJECT MANAGER REVIEW (IFR) - NOT APPROVED | Rev 3.1 | D16: Classification | E16: Fictional Demonstration Data
A18: FOUR-TEST RESULT TILES (linked to the Four-Test Scorecard)
A19: T1 Evidence and version | B19: T2 Records agree | C19: T3 Configured NEC4 route and clock | D19: T4 Human authority
A20: ='Four-Test Scorecard'!D5 -> 0 | B20: ='Four-Test Scorecard'!D6 -> 0 | C20: ='Four-Test Scorecard'!D7 -> 0 | D20: ='Four-Test Scorecard'!D8 -> 2
A21: ='Four-Test Scorecard'!E5 -> CRITICAL FAILURE | B21: ='Four-Test Scorecard'!E6 -> CRITICAL FAILURE | C21: ='Four-Test Scorecard'!E7 -> CRITICAL FAILURE | D21: ='Four-Test Scorecard'!E8 -> PASS
A23: CONTROL LOGIC AND ROUTE (formula-driven)
A24: Critical exceptions | B24: ='Exceptions and Actions'!$C$13 -> 2
A25: Total score (max 8) | B25: =SUM(A20:D20) -> 2
A26: Critical-failure count | B26: =COUNTIF(A20:D20,0) -> 3
A27: Reserved-authority failure | B27: =IF(D20=0,"YES","NO") -> NO
A28: Material record conflict | B28: =IF(COUNTIF('Clause 64.1 Triggers'!$D$5:$D$8,"TRIGGER_INDICATED")>0,"YES","NO") -> NO
A29: Mandatory evidence missing | B29: =IF(COUNTIF('Evidence Register'!$A$5:$A$27,"MISSING - MANDATORY")>0,"YES","NO") -> YES
A30: Critical route/clock failure | B30: =IF(C20=0,"YES","NO") -> YES
A31: Bounded limitations (score 1) | B31: =COUNTIF(A20:D20,1) -> 0
A32: Failing NEC4 controls | B32: ='NEC4 Control Cross-Reference'!$D$18 -> 2
A34: RECOMMENDED DECISION ROUTE | B34: =IF(B27="YES","REFER TO PROJECT MANAGER",IF(B28="YES","STOP / RECONCILE",IF(B29="YES","REWORK EVIDENCE PACK",IF(B30="YES","STOP / ESCALATE",IF(B31>0,"READY WITH CONDITIONS","READY FOR PROJECT MANAGER REVIEW"))))) -> REWORK EVIDENCE PACK
A35: Route priority applied in order: reserved-authority failure, material record conflict, mandatory evidence missing, critical route/clock failure, any score of 1, otherwise ready. A score of 0 overrides the total score.
A37: POSITION, EXPOSURE AND NEXT ACTION
A38: Four-Test Result | B38: CONFIGURED FOUR-TEST RESULT: CRITICAL FAILURE - T1, T2 and T3 score 0. A score of 0 determines the route irrespective of the total score.
A39: Configured NEC4 Process-Assurance Result | B39: CONFIGURED NEC4 PROCESS CONTROL FAILURE - REWORK. Two critical content controls (NEC-05 Clause 62.2 and NEC-10 programme alteration) fail on absent evidence. Ten controls are satisfied, conditional, pending-not-due or correctly reserved for Project Manager judgement. This is a statement about the configured demonstration controls only and is not a statement of NEC4 or legal compliance.
A40: Clause 64.1 Trigger Summary | B40: Four trigger checks reported separately. One NOT_TRIGGERED (trigger 1). Three reserved for PROJECT MANAGER JUDGEMENT (triggers 2, 3 and 4), each because the current programme record required to complete the check is absent. No trigger is asserted to have contractual effect.
A41: Clause 62.2 content check | B41: EXPLICITLY CHECKED - NOT EVIDENCED IN THE ASSURANCE PACK. Assessment details are present. No current programme or separate programme-alteration record is available in the assurance pack. The assistant cannot determine whether the record was not submitted by the Contractor or was omitted when the assurance pack was assembled.
A42: Schedule effect evidenced by the records | B42: 10 working days stated in the quotation, forecast, risk, change and event records. UNVERIFIED - no current programme record available to measure it.
A43: Commercial exposure evidenced by the records | B43: GBP 185,000, reconciling across quotation, forecast, risk, change and event records. Not assessed or accepted.
A44: Missing mandatory evidence | B44: P6_Activity_Export_UP13.csv | PROG-UP13 | rev UP13 | owner Planning Manager
A45: Next action | B45: Direct retrieval and registration of P6_Activity_Export_UP13.csv rev UP13, or the specific programme alteration relied on by Quotation Rev B, then reissue the pack for review.
A46: Next action due | B46: 2026-04-02 - assurance rework target, not a contractual deadline. Configured RC-03 Project Manager response date: 2026-04-11.
A47: Critical exceptions raised | B47: 2 (EX-01 missing mandatory record; EX-02 Clause 62.2 content not evidenced). Total exceptions 6.
A48: Decision owner | B48: Elena Brooks - NEC4 Project Manager - retains every contractual decision on CE-018
A50: Fictional Demonstration Data. Configured demonstration controls only - not legal advice and not a statement of NEC4 or legal compliance. Prepared by the CE-018 Project Controls Assurance Assistant (non-contractual support) for Elena Brooks, NEC4 Project Manager.

Sheet Evidence Register
A1: EVIDENCE REGISTER
A2: Registered against Source_Register.csv | SRC-001 | rev 3.0 | 11 Context records and 12 registered scenario records
A4: Status | B4: Record ID | C4: File name | D4: Record type | E4: Revision | F4: Version status | G4: Owner / custodian | H4: Intended use | I4: Citation reference
A5: PRESENT | B5: SRC-001 | C5: Source_Register.csv | D5: Source register | E5: 3.0 | F5: Current | G5: Project Controls Lead | H5: Controls the approved Context and scenario evidence | I5: Source_Register.csv | SRC-001 | rev 3.0
A6: PRESENT | B6: CTRL-001 | C6: CE018_Control_Brief.txt | D6: Control brief | E6: 3.0 | F6: Current | G6: Project Controls Lead | H6: Permitted task, assurance method and prohibited actions | I6: CE018_Control_Brief.txt | CTRL-001 | rev 3.0
A7: PRESENT | B7: CTRL-002 | C7: Actor_Authority_Matrix.csv | D7: Authority matrix | E7: 2.1 | F7: Current | G7: Project Controls Lead | H7: Named actors, responsibilities and retained authority | I7: Actor_Authority_Matrix.csv | CTRL-002 | rev 2.1
A8: PRESENT | B8: CTRL-003 | C8: Route_Clock_Rules.csv | D8: Route and clock rules | E8: 3.0 | F8: Current | G8: NEC4 Project Manager | H8: Configured clause-linked periods and due dates | I8: Route_Clock_Rules.csv | CTRL-003 | rev 3.0
A9: PRESENT | B9: CTRL-005 | C9: Four_Test_Checklist.csv | D9: Assurance checklist | E9: 3.0 | F9: Current | G9: Project Controls Lead | H9: Four assurance tests, scoring and dependencies | I9: Four_Test_Checklist.csv | CTRL-005 | rev 3.0
A10: PRESENT | B10: CTRL-006 | C10: Expected_Response_Structure.txt | D10: Response structure | E10: 3.0 | F10: Current | G10: Project Controls Lead | H10: Required report, scorecard and JSON structure | I10: Expected_Response_Structure.txt | CTRL-006 | rev 3.0
A11: PRESENT | B11: CTRL-007 | C11: NEC4_Decision_Readiness_Control_Matrix.csv | D11: NEC4 control matrix | E11: 1.0 | F11: Current | G11: NEC4 Project Manager | H11: Configured procedural controls and Clause 64.1 triggers | I11: NEC4_Decision_Readiness_Control_Matrix.csv | CTRL-007 | rev 1.0
A12: PRESENT | B12: WBS-001 | C12: WBS_Hierarchy.csv | D12: WBS | E12: 1.0 | F12: Current | G12: Planning Manager | H12: Project and work-package hierarchy | I12: WBS_Hierarchy.csv | WBS-001 | rev 1.0
A13: PRESENT | B13: CBS-001 | C13: CBS_Hierarchy.csv | D13: CBS | E13: 1.0 | F13: Current | G13: Cost Manager | H13: Cost hierarchy | I13: CBS_Hierarchy.csv | CBS-001 | rev 1.0
A14: PRESENT | B14: XWALK-001 | C14: CE018_WBS_Programme_CBS_Crosswalk.csv | D14: Crosswalk | E14: 1.0 | F14: Current | G14: Project Controls Lead | H14: Links CE-018 to WBS, activities and CBS | I14: CE018_WBS_Programme_CBS_Crosswalk.csv | XWALK-001 | rev 1.0
A15: PRESENT | B15: CASE-001 | C15: CE018_Event_Record.csv | D15: Event record | E15: 1.1 | F15: Current | G15: Project Controls Lead | H15: Controlled CE-018 facts, status and cut-off | I15: CE018_Event_Record.csv | CASE-001 | rev 1.1
... A27: PRESENT | B27: CHG-018 | C27: Change_Register.csv | D27: Change register | E27: 5 | F27: Current | G27: Change Manager | H27: Status, decision owner, next action and expected effect | I27: Change_Register.csv | CHG-018 | rev 5
A29: Deliberate S2 omission: | B29: Source_Register.csv | SRC-001 | rev 3.0 | row PROG-UP13 - required record, deliberately omitted in S2 | Effect: Current-position, programme-alteration and Clause 62.2 linkage checks cannot be completed. AP12 has not been substituted.
A30: Packaging defects: | B30: None identified. No duplicate, mis-revisioned, unregistered or mixed-scenario evidence file is attached. S3 conflict records (FCST-P07-X, RISK-044-X) are absent as required.
A31: Excluded assets: | B31: Five branding PNG assets and the branding/output-controls note are formatting assets only. Not inventoried, cited, scored or added to the Source Register.

Sheet Cross-Record Reconciliation
A1: CROSS-RECORD RECONCILIATION
A2: AP12 planned position against the current position | UP13 absent - no value inferred | Values not averaged
A4: WBS ID | B4: WBS name | C4: Activity ID | D4: Activity name | E4: CBS code | F4: Cost element | G4: AP12 planned position (PROG-AP12 rev AP12) | H4: UP13 current position (PROG-UP13 rev UP13) | I4: Crosswalk GBP | J4: Quotation GBP | K4: Forecast GBP | L4: Variance GBP | M4: Schedule claim (wd) | N4: Reconciliation status
A5: WSAE.20.10 | B5: Platform 4 Access | C5: WSAE-A1200 | D5: Establish Platform 4 worksite access | E5: WSAE-C210 | F5: Access / Possession Standby | G5: Start Milestone planned 2026-03-04; total float 0; variance to accepted finish 0 | H5: MISSING EVIDENCE - not inferred | I5: 25000 | J5: 25000 | K5: 25000 | L5: =J5-K5 -> 0 | M5: 10 | N5: Cost reconciled; time position unverifiable
A6: WSAE.30.10 | B6: Worksite Establishment | C6: WSAE-A1300 | D6: Platform 4 enabling works | E6: WSAE-C310 | F6: Direct Labour | G6: Planned 2026-03-05 to 2026-03-18; original duration 10 d; total float 2 | H6: MISSING EVIDENCE - not inferred | I6: 55000 | J6: 55000 | K6: 55000 | L6: =J6-K6 -> 0 | M6: 10 | N6: Cost reconciled; time position unverifiable
A7: WSAE.30.10 | B7: Worksite Establishment | C7: WSAE-A1300 | D7: Platform 4 enabling works | E7: WSAE-C320 | F7: Plant and Equipment | G7: Planned 2026-03-05 to 2026-03-18; original duration 10 d; total float 2 | H7: MISSING EVIDENCE - not inferred | I7: 35000 | J7: 35000 | K7: 35000 | L7: =J7-K7 -> 0 | M7: 10 | N7: Cost reconciled; time position unverifiable
A8: WSAE.30.20 | B8: Temporary Services | C8: WSAE-A1400 | D8: Install temporary services | E8: WSAE-C510 | F8: Time-Related Overheads | G8: Planned 2026-03-19 to 2026-03-27; original duration 7 d; total float 0 | H8: MISSING EVIDENCE - not inferred | I8: 50000 | J8: 50000 | K8: 50000 | L8: =J8-K8 -> 0 | M8: 10 | N8: Cost reconciled; extended-preliminaries basis cannot be tested against a revised finish
A9: WSAE.10 | B9: Project Management and Controls | C9: WSAE-M9000 | D9: Platform 4 worksite ready | E9: WSAE-C610 | F9: CE-018 Risk Allowance | G9: Finish Milestone planned 2026-03-27; total float 0; variance to accepted finish 0 | H9: MISSING EVIDENCE - not inferred | I9: 20000 | J9: 20000 | K9: 20000 | L9: =J9-K9 -> 0 | M9: 10 | N9: Cost reconciled; milestone slip cannot be measured
A10: TOTAL | I10: =SUM(I5:I9) -> 185000 | J10: =SUM(J5:J9) -> 185000 | K10: =SUM(K5:K9) -> 185000 | L10: =SUM(L5:L9) -> 0 | N10: Quotation, forecast, crosswalk, risk and change all state GBP 185,000 and 10 working days. No conflict. Time position unverifiable.
A12: Whole-record comparison
A13: Record | B13: Record ID | C13: Revision | D13: Time position | E13: Cost position
A14: Accepted Programme | B14: PROG-AP12 | C14: AP12 | D14: Planned only; variance to accepted finish 0 at data date 2026-02-20 | E14: Not a cost record
A15: Current programme update | B15: PROG-UP13 | C15: UP13 | D15: MISSING EVIDENCE - not inferred | E15: MISSING EVIDENCE - not inferred
A16: Quotation Rev B | B16: QUOT-CE018-REVB | C16: B | D16: 10 working days claimed | E16: GBP 185,000
A17: Cost forecast P07 | B17: FCST-P07 | C17: P07 | D17: 10 working days | E17: GBP 185,000
A18: Risk register | B18: RISK-044 | C18: 7 | D18: 10 working days | E18: GBP 185,000
A19: Change register | B19: CHG-018 | C19: 5 | D19: 10 working days | E19: GBP 185,000
A20: Event record | B20: CASE-001 | C20: 1.1 | D20: 10 working days | E20: GBP 185,000
A22: Current-position checks that cannot be completed
A23: 1. | B23: Actual start and finish of WSAE-A1200, WSAE-A1300, WSAE-A1400 and WSAE-M9000.
A24: 2. | B24: Current Late Finish dates and total float against the AP12 position.
A25: 3. | B25: Measured variance to the accepted finish supporting the claimed 10 working-day effect (AP12 records variance 0 for every CE-018 activity at its 2026-02-20 data date).
A26: 4. | B26: Whether remaining work is altered and, if so, the required alterations to the Accepted Programme submitted with the quotation.
A27: 5. | B27: Whether the full access date of 2026-03-18 in CASE-001 is reflected in a current programme record.
A28: 6. | B28: The revised finish underpinning the WSAE-C510 extended time-related overhead of GBP 50,000.
A29: 7. | B29: Alignment between the current programme data date and the P07 forecast data date of 2026-03-31.
A31: Structural integrity
A32: • Every WBS identifier in the crosswalk exists in WBS_Hierarchy.csv | WBS-001 | rev 1.0 (WSAE.10, WSAE.20.10, WSAE.30.10, WSAE.30.20).
A33: • Every CBS account in the crosswalk exists in CBS_Hierarchy.csv | CBS-001 | rev 1.0 (WSAE-C210, WSAE-C310, WSAE-C320, WSAE-C510, WSAE-C610).
A34: • Every programme activity in the crosswalk exists in AP12 (WSAE-A1200, WSAE-A1300, WSAE-A1400, WSAE-M9000). Existence in UP13 could not be checked.
A35: • WSAE-M9000 maps to WBS WSAE.10 in both P6_Activity_Export_AP12.csv | PROG-AP12 | rev AP12 | row WSAE-M9000 and CE018_WBS_Programme_CBS_Crosswalk.csv | XWALK-001 | rev 1.0 | row 5.
A36: • Every quoted and forecast value links to a valid CBS account. No relationship has been created or repaired.

Sheet Four-Test Scorecard
A1: FOUR-TEST SCORECARD
A2: CE-018 | Scenario S2 - current programme evidence missing | Scores applied from the S2 evidence only
A4: Test | B4: Test name | C4: Purpose - what is tested and why it matters | D4: Score | E4: Status | F4: Finding | G4: Evidence citation | H4: Critical failure | I4: Consequence | J4: Retest requirement
A5: T1 | B5: Evidence and version | C5: Confirm that every required record is present, approved, current and used for its stated purpose | D5: 0 | E5: CRITICAL FAILURE | F5: Eleven of twelve registered scenario evidence records are present at their approved revision. PROG-UP13 is the one mandatory record absent. All eleven permanent Context records are also present at their approved revision and correctly classified. The absent record is P6_Activity_Export_UP13.csv, revision UP13. Source_Register.csv rev 3.0 records PROG-UP13 as Required = Yes. Its absence is the deliberate S2 test condition, not an accidental packaging defect, but the score is applied from the evidence available. AP12 has not been substituted. | G5: Source_Register.csv | SRC-001 | rev 3.0 | row PROG-UP13; Four_Test_Checklist.csv | CTRL-005 | rev 3.0 | row T1 | H5: =IF(D5=0,"YES","NO") -> YES | I5: A mandatory record is missing. Route: REWORK EVIDENCE PACK. The pack cannot support an unqualified decision on the current programme position. | J5: Retest T1 in full once P6_Activity_Export_UP13.csv rev UP13 is registered and supplied.
A6: T2 | B6: Records agree | C6: Test whether programme, quotation, forecast, risk and change records describe the same time, cost and event impact | D6: 0 | E6: CRITICAL FAILURE | F6: No conflict exists between the records present: quotation, forecast, risk, change and event records all state GBP 185,000 and 10 working days, and the quotation reconciles line by line to the controlled crosswalk. The test nevertheless fails because the required programme alteration is missing: the claimed 10 working-day effect and the extended time-related overhead cannot be tested against any current programme, and AP12 records variance to accepted finish of 0 for every CE-018 activity at its 2026-02-20 data date. Four_Test_Checklist rev 3.0 scores a missing programme alteration that prevents reliable review as a critical failure. | G6: CE018_Quotation_RevB.csv | QUOT-CE018-REVB | rev B; Cost_Forecast_P07.csv | FCST-P07 | rev P07; Risk_Register.csv | RISK-044 | rev 7; Change_Register.csv | CHG-018 | rev 5; P6_Activity_Export_AP12.csv | PROG-AP12 | rev AP12; Four_Test_Checklist.csv | CTRL-005 | rev 3.0 | row T2 | H6: =IF(D6=0,"YES","NO") -> YES | I6: The time position underpinning the quotation cannot be reconciled. This is an evidence gap, not a record conflict, so the reconciliation route does not apply. | J6: Rerun the full cross-record reconciliation, including all seven incomplete current-position checks, once UP13 is supplied.
A7: T3 | B7: Configured NEC4 route and clock | C7: Check the configured event route, notice sequence, required content and response periods | D7: 0 | E7: CRITICAL FAILURE | F7: Every configured response period is satisfied or correctly pending-not-due: RC-EW recorded 2026-02-25 against a 2026-02-25 due date; RC-01 PM response 2026-03-12 on the configured date; RC-02 quotation submitted 2026-03-28 against a 2026-04-02 due date; RC-03 pending and not due at the 2026-03-31 cut-off. The failure is confined to the RC-02 content limb: the required action includes the required alterations to the Accepted Programme, and the listed evidence record PROG-UP13 is absent. Clause 64.1 trigger check 3 therefore cannot be closed, which Four_Test_Checklist rev 3.0 scores as a critical failure. | G7: Route_Clock_Rules.csv | CTRL-003 | rev 3.0 | rows RC-EW, RC-00, RC-01, RC-02, RC-03; Four_Test_Checklist.csv | CTRL-005 | rev 3.0 | row T3 | H7: =IF(D7=0,"YES","NO") -> YES | I7: No clock is overdue. An unresolved Clause 64.1 trigger check and an unevidenced Clause 62.2 content requirement remain. Contractual effect is reserved to the Project Manager. | J7: Rerun RC-02 content verification and NEC-05, NEC-09, NEC-10 and NEC-11 once UP13 is supplied. Re-run RC-03 after 2026-04-11.
A8: T4 | B8: Human authority | C8: Confirm that notification, assessment, acceptance, instruction and implementation remain with authorised roles | D8: 2 | E8: PASS | F8: No reserved contractual action has been requested or taken. The assistant has extracted, linked, compared, cited and flagged only. The Contractor's CE-018 notification is recorded as evidence. The assistant did not issue a notification, determine whether CE-018 is a compensation event, or take any other reserved contractual action - no entitlement was determined, no quotation assessed or accepted, no contractual communication issued or drafted in another person's name, and CE-018 was not implemented. The retained decision and the pending RC-03 response remain with Elena Brooks, and the change record records the decision status as not yet decided. | G8: Actor_Authority_Matrix.csv | CTRL-002 | rev 2.1 | rows EB, SK, AI; CE018_Control_Brief.txt | CTRL-001 | rev 3.0 | Retained Authority; Change_Register.csv | CHG-018 | rev 5 | field decision_status | H8: =IF(D8=0,"YES","NO") -> NO | I8: Authority control is evidenced. No authority-based route override arises. | J8: Retest if any output or request would take a reserved contractual action.
A10: Total score | D10: =SUM(D5:D8) -> 2 | F10: Maximum 8. A score of 0 determines the route irrespective of the total score.
A11: Critical failures | D11: =COUNTIF(D5:D8,0) -> 3 | F11: Count of tests scoring 0. Each is reported in full; the most restrictive route applies.
A13: Scoring key: 2 = Pass (control evidenced) | 1 = Bounded limitation (owner and deadline identified, review not prevented) | 0 = Critical failure (evidence missing, records materially conflict, configured route or date failed, or authority exceeded).

Sheet NEC4 Control Cross-Reference
A1: NEC4 DECISION-READINESS CONTROL CROSS-REFERENCE
A2: All 12 controls in NEC4_Decision_Readiness_Control_Matrix.csv | CTRL-007 | rev 1.0 executed
A4: Control | B4: Control group | C4: NEC4 ECC reference | D4: Four-test link | E4: Decision-readiness question | F4: Evidence | G4: Result | H4: Finding | I4: Consequence | J4: Accountable owner
A5: NEC-01 | B5: Early warning | C5: 15.1 | D5: T1/T3 | E5: Is there dated evidence that the access risk was warned when it became apparent? | F5: Email_01_Access_Risk_2026-02-24.eml | CORR-001 | rev 1.0; Email_02_EW006_2026-02-25.eml | EW-006 | rev 1.0; Route_Clock_Rules.csv | CTRL-003 | rev 3.0 | row RC-EW | G5: CONDITIONAL | H5: Both dated records are present and the early warning was recorded on 2026-02-25, one day after the initial risk email of 2026-02-24, against the configured RC-EW due date of 2026-02-25. The third required evidence item, an Early Warning Register reference, is not a registered record in Source_Register.csv rev 3.0 and could not be checked. | I5: Bounded administrative limitation. Does not prevent review. Whether the notice was sufficiently prompt is a contractual judgement reserved to the Project Manager. | J5: Sofia Khan - Project Controls Lead
A6: NEC-02 | B6: Access and event basis | C6: 33.1 / 60.1(2) | D6: T1/T3 | E6: Do the Accepted Programme and access record evidence the planned access date and the actual restriction? | F6: P6_Activity_Export_AP12.csv | PROG-AP12 | rev AP12 | row WSAE-A1200; Email_03_Access_Restriction_2026-03-04.eml | ACC-004 | rev 1.0; Email_04_CE018_Notification_2026-03-05.eml | CE-018 | rev 1.0 | G6: EVIDENCED_PM_DETERMINATION | H6: AP12 shows milestone WSAE-A1200 planned for 2026-03-04 on WBS WSAE.20.10. ACC-004 confirms that the planned eight-hour access was not available on that date and that a two-hour escorted window from 03:00 to 05:00 was provided. The event description is consistent across the access record, the notification and the controlled event record. | I6: Candidate event basis is evidenced and referred to the Project Manager. The assistant does not decide whether a compensation event exists. | J6: Elena Brooks - NEC4 Project Manager
A7: NEC-03 | B7: Contractor notification | C7: 61.3 | D7: T1/T3 | E7: Was the Contractor notification separately recorded, correctly routed and within the configured time-bar control? | F7: Email_04_CE018_Notification_2026-03-05.eml | CE-018 | rev 1.0; Email_02_EW006_2026-02-25.eml | EW-006 | rev 1.0; Source_Register.csv | SRC-001 | rev 3.0 | G7: PASSED | H7: CE-018 is registered as a separate record from EW-006 and was notified on 2026-03-05, one day after the restriction event of 2026-03-04. It was routed from the Contractor Delivery Lead to the Project Manager. Elapsed time is reported as an objective calculation only. | I7: No time-bar concern is indicated on the configured evidence. Any exception to a time bar is a Project Manager judgement. | J7: Elena Brooks - NEC4 Project Manager
A8: NEC-04 | B8: PM notification response | C8: 61.4 | D8: T3 | E8: Did the Project Manager respond within the configured one-week period? | F8: Email_05_PM_Response_2026-03-12.eml | PMR-018 | rev 1.0; Route_Clock_Rules.csv | CTRL-003 | rev 3.0 | row RC-01 | G8: PASSED | H8: Trigger date 2026-03-05, configured period 7 days, due date 2026-03-12, actual date 2026-03-12. The response was recorded on the configured date. | I8: No escalation arises from this clock. | J8: Elena Brooks - NEC4 Project Manager
A9: NEC-05 | B9: Quotation content | C9: 62.2 | D9: T1/T2/T3 | E9: Does the quotation pack contain assessment details and, where remaining work is altered, the required alterations to the Accepted Programme? | F9: CE018_Quotation_RevB.csv | QUOT-CE018-REVB | rev B (5 lines by WBS, activity and CBS); Email_06_Quotation_Submission_2026-03-28.eml | QSUB-018 | rev 1.0; P6_Activity_Export_AP12.csv | PROG-AP12 | rev AP12; PROG-UP13 ABSENT | G9: FAILED_REWORK | H9: Assessment details are present: five priced lines totalling GBP 185,000, each linked to a WBS identifier, a programme activity, a CBS account and a stated basis. The required alterations to the Accepted Programme are NOT present in the assurance pack. No current programme record, and no separate programme-alteration record, is available in the pack. QSUB-018 states that the submission links current update UP13, but that record is absent and the statement cannot be verified. The quotation asserts a 10 working-day effect that no programme record in the pack supports. | I9: Clause 62.2 is explicitly checked and is NOT EVIDENCED IN THE ASSURANCE PACK. Assessment details are present. No current programme or separate programme-alteration record is available in the assurance pack. The assistant cannot determine whether the record was not submitted by the Contractor or was omitted when the assurance pack was assembled. The control is retained as FAILED_REWORK under the configured assurance controls: rework the evidence pack before any Project Manager decision on content. Whether the assessment is contractually correct remains a Project Manager judgement. | J9: Marcus Reed - Contractor Delivery Lead / Planning Manager (record custodian)
A10: NEC-06 | B10: Quotation submission clock | C10: 62.3 | D10: T3 | E10: Was the quotation and assessment detail submitted within the configured three-week period? | F10: Email_05_PM_Response_2026-03-12.eml | PMR-018 | rev 1.0; Email_06_Quotation_Submission_2026-03-28.eml | QSUB-018 | rev 1.0; Route_Clock_Rules.csv | CTRL-003 | rev 3.0 | row RC-02 | G10: PASSED | H10: Trigger date 2026-03-12, configured period 21 days, due date 2026-04-02, actual submission 2026-03-28. The clock limb is satisfied. The content limb is assessed separately under NEC-05 and NEC-10; a timely email does not prove that the Clause 62.2 content requirement is met. | I10: No clock-based Clause 64.1 assessment trigger arises from lateness. | J10: Marcus Reed - Contractor Delivery Lead
A11: NEC-07 | B11: PM quotation response | C11: 62.3 / 62.6 | D11: T3/T4 | E11: Is the Project Manager response recorded, or correctly classified as pending-not-due at the cut-off? | F11: Route_Clock_Rules.csv | CTRL-003 | rev 3.0 | row RC-03; CE018_Event_Record.csv | CASE-001 | rev 1.1 | field assessment_cutoff; Change_Register.csv | CHG-018 | rev 5 | field decision_status | G11: PENDING_NOT_DUE | H11: Trigger date 2026-03-28, configured period 14 days, due date 2026-04-11. At the evidence cut-off of 2026-03-31 the response is pending and not overdue. No decision record DEC-CE018 exists and none has been inferred or drafted. | I11: No escalation at the cut-off. The response becomes overdue only after 2026-04-11. The decision is not made or anticipated by the assistant. | J11: Elena Brooks - NEC4 Project Manager
A12: NEC-08 | B12: Clause 64.1 trigger 1 | C12: 64.1 - late/missing quotation | D12: T2/T3 | E12: Has the Contractor failed to submit the quotation and assessment details within the permitted time? | F12: Email_06_Quotation_Submission_2026-03-28.eml | QSUB-018 | rev 1.0; CE018_Quotation_RevB.csv | QUOT-CE018-REVB | rev B; Route_Clock_Rules.csv | CTRL-003 | rev 3.0 | row RC-02 | G12: NOT_TRIGGERED | H12: A quotation with priced assessment details was submitted on 2026-03-28, within the configured due date of 2026-04-02. | I12: No lateness-based assessment trigger is indicated on the configured evidence. | J12: Elena Brooks - NEC4 Project Manager
A13: NEC-09 | B13: Clause 64.1 trigger 2 | C13: 64.1 - incorrect assessment | D13: T2/T3 | E13: Is there a material inconsistency or unsupported basis that may indicate the Contractor's assessment is not correct? | F13: CE018_Quotation_RevB.csv | QUOT-CE018-REVB | rev B; Cost_Forecast_P07.csv | FCST-P07 | rev P07; Risk_Register.csv | RISK-044 | rev 7; Change_Register.csv | CHG-018 | rev 5; CE018_WBS_Programme_CBS_Crosswalk.csv | XWALK-001 | rev 1.0; PROG-UP13 ABSENT | G13: PM_JUDGEMENT | H13: No inconsistency was detected between the records present: cost reconciles at GBP 185,000 across all five records and every line links to a valid WBS, activity and CBS. The test could not be completed because the time element of the assessment - the claimed 10 working-day effect and the extended preliminaries basis - has no current programme record against which it can be tested. | I13: The assistant reports an incomplete verification, not a defect. Only the Project Manager decides whether the assessment is contractually correct. | J13: Elena Brooks - NEC4 Project Manager
A14: NEC-10 | B14: Clause 64.1 trigger 3 | C14: 62.2 / 64.1 - programme alteration missing | D14: T1/T2/T3 | E14: Where the event alters remaining work, was the required programme or alteration submitted with the quotation pack? | F14: Email_06_Quotation_Submission_2026-03-28.eml | QSUB-018 | rev 1.0; P6_Activity_Export_AP12.csv | PROG-AP12 | rev AP12; Source_Register.csv | SRC-001 | rev 3.0 | row PROG-UP13; PROG-UP13 ABSENT | G14: FAILED_REWORK | H14: The quotation asserts that remaining work is altered by 10 working days, but no current programme record and no separate programme-alteration record is present in or linked to the pack. QSUB-018 asserts a link to UP13; the record is absent, so the assertion cannot be verified. The assistant cannot distinguish an evidence-pack assembly omission from a Contractor submission failure, and does not assert either. | I14: Evidence-pack rework is required. The contractual status of this Clause 64.1 trigger is reserved to the Project Manager and is reported separately. | J14: Planning Manager (record custodian) via Sofia Khan - Project Controls Lead
A15: NEC-11 | B15: Clause 64.1 trigger 4 | C15: 31.1 / 31.3 / 32.2 / 64.1 - latest programme not accepted | D15: T1/T3 | E15: Is an Accepted Programme available and is any relevant non-acceptance status identified? | F15: P6_Activity_Export_AP12.csv | PROG-AP12 | rev AP12 | field programme_status 'Accepted Programme'; CE018_Event_Record.csv | CASE-001 | rev 1.1 | fields accepted_programme, current_programme_update; PROG-UP13 ABSENT | G15: PM_JUDGEMENT | H15: An Accepted Programme is available: AP12 at data date 2026-02-20, recorded as the Accepted Programme in both the P6 export and the controlled event record. No non-acceptance record is present. The acceptance or non-acceptance status of the later controlled update UP13 could not be checked because the record is absent. UP13 has not been treated as accepted, and AP12 has not been treated as a current update. | I15: The AP12 limb is satisfied. The latest-programme limb is untested. Contractual status is reserved to the Project Manager. | J15: Elena Brooks - NEC4 Project Manager
A16: NEC-12 | B16: Retained human authority | C16: Clauses 61-64 and Authority Matrix | D16: T4 | E16: Are the remaining notification, assessment, acceptance, instruction and implementation actions reserved to the named NEC4 role? | F16: Actor_Authority_Matrix.csv | CTRL-002 | rev 2.1 | rows EB, SK, AI; CE018_Control_Brief.txt | CTRL-001 | rev 3.0 | Retained Authority and Prohibited Actions | G16: PASSED | H16: Every remaining contractual action - the response to the quotation, the assessment, any acceptance and any implementation of CE-018 - is recorded against Elena Brooks. The assistant has prepared a cited pack and taken no reserved action. No communication has been drafted in another person's name. | I16: Authority control satisfied. No stop-and-refer arises on authority grounds. | J16: Elena Brooks - NEC4 Project Manager
A18: Controls failing | D18: =COUNTIF(G5:G16,"FAILED_REWORK") -> 2
A19: Clause 62.2 check | D19: EXPLICITLY CHECKED - NOT EVIDENCED IN THE ASSURANCE PACK. Assessment details are present. No current programme or separate programme-alteration record is available in the assurance pack. The assistant cannot determine whether the record was not submitted by the Contractor or was omitted when the assurance pack was assembled.
A20: Process result | D20: CONFIGURED NEC4 PROCESS CONTROL FAILURE - REWORK. Two critical content controls (NEC-05 Clause 62.2 and NEC-10 programme alteration) fail on absent evidence. Ten controls are satisfied, conditional, pending-not-due or correctly reserved for Project Manager judgement. This is a statement about the configured demonstration controls only and is not a statement of NEC4 or legal compliance.

Sheet Clause 64.1 Triggers
A1: CLAUSE 64.1 INTERVENTION TRIGGER CHECKS
A2: All four checks reported separately | The assistant does not decide that any trigger has contractual effect
A4: Control | B4: Trigger | C4: Evidence finding | D4: Contractual status | E4: Basis
A5: NEC-08 | B5: Trigger 1 - Contractor has not submitted a quotation and assessment details within the permitted time | C5: Quotation Rev B with five priced assessment lines submitted 2026-03-28 against the configured RC-02 due date of 2026-04-02. | D5: NOT_TRIGGERED | E5: Route_Clock_Rules.csv | CTRL-003 | rev 3.0 | row RC-02; Email_06_Quotation_Submission_2026-03-28.eml | QSUB-018 | rev 1.0; CE018_Quotation_RevB.csv | QUOT-CE018-REVB | rev B
A6: NEC-09 | B6: Trigger 2 - Contractor has not assessed the compensation event correctly | C6: No inconsistency detected between the records present; all five records state GBP 185,000 and 10 working days and reconcile line by line to the crosswalk. The time element could not be tested because no current programme record is available. | D6: PROJECT MANAGER JUDGEMENT | E6: NEC4_Decision_Readiness_Control_Matrix.csv | CTRL-007 | rev 1.0 | row NEC-09 - only the Project Manager decides whether the assessment is contractually correct. The assistant reports an incomplete verification and makes no assertion of correctness or incorrectness.
A7: NEC-10 | B7: Trigger 3 - Contractor has not submitted a programme or alterations to a programme which the contract requires | C7: No current programme record and no separate programme-alteration record is present in or linked to the quotation pack. QSUB-018 states that the submission links current update UP13; the record PROG-UP13 is absent from the pack and the statement is unverified. Source_Register.csv rev 3.0 records PROG-UP13 as a required record deliberately omitted in S2. | D7: PROJECT MANAGER JUDGEMENT | E7: The objective evidence establishes only that the record is absent from the assurance pack. It does not establish whether the Contractor failed to submit it or whether the pack was assembled without it. That distinction must be resolved by retrieving PROG-UP13, after which this trigger is retested. The assistant does not decide that this trigger has contractual effect.
A8: NEC-11 | B8: Trigger 4 - Project Manager has not accepted the latest programme for one of the reasons stated in the contract | C8: AP12 is available and recorded as the Accepted Programme at data date 2026-02-20. No non-acceptance record is present. The submission and acceptance status of the later controlled update UP13 could not be checked because the record is absent. | D8: PROJECT MANAGER JUDGEMENT | E8: P6_Activity_Export_AP12.csv | PROG-AP12 | rev AP12; CE018_Event_Record.csv | CASE-001 | rev 1.1 | field current_programme_update. AP12 has not been treated as a current update and UP13 has not been treated as accepted.
A10: Summary | B10: Four trigger checks reported separately. One NOT_TRIGGERED (trigger 1). Three reserved for PROJECT MANAGER JUDGEMENT (triggers 2, 3 and 4), each because the current programme record required to complete the check is absent. No trigger is asserted to have contractual effect.

Sheet Exceptions and Actions
A1: EXCEPTIONS AND ACTIONS
A2: Assurance exceptions and pending actions reported separately | Administrative observations are non-actionable
A4: A. ASSURANCE EXCEPTIONS
A5: ID | B5: Classification | C5: Issue | D5: Evidence | E5: Consequence | F5: Accountable owner | G5: Required action | H5: Due date | I5: Date basis | J5: Action status | K5: Retest requirement
A6: EX-01 | B6: CRITICAL - Mandatory evidence missing | C6: The mandatory current controlled programme update P6_Activity_Export_UP13.csv (PROG-UP13, revision UP13) is not present in the S2 evidence pack. | D6: Source_Register.csv | SRC-001 | rev 3.0 | row PROG-UP13 | E6: T1, T2 and T3 score 0; NEC-05 and NEC-10 fail; Clause 64.1 triggers 2, 3 and 4 cannot be closed; seven current-position reconciliation checks cannot be completed. | F6: Planning Manager (registered record owner), routed by Sofia Khan - Project Controls Lead | G6: Supply P6_Activity_Export_UP13.csv at approved revision UP13, controlled status current, with its data date, actual dates, Late Finish dates, total float and forecast; or supply the specific programme alteration record submitted with Quotation Rev B. | H6: 2026-04-02 | I6: Assurance rework target - not a contractual deadline | J6: Open | K6: T1, T2, T3; NEC-05, NEC-09, NEC-10, NEC-11; Clause 64.1 triggers 2, 3 and 4; full Cross-Record Reconciliation
A7: EX-02 | B7: CRITICAL - Clause 62.2 content not evidenced | C7: The quotation pack does not contain, and is not linked to, the required alterations to the Accepted Programme. Assessment details are present; the programme content requirement is not evidenced. | D7: CE018_Quotation_RevB.csv | QUOT-CE018-REVB | rev B; Email_06_Quotation_Submission_2026-03-28.eml | QSUB-018 | rev 1.0; NEC4_Decision_Readiness_Control_Matrix.csv | CTRL-007 | rev 1.0 | row NEC-05 | E7: NEC-05 FAILED_REWORK; NEC-10 FAILED_REWORK; the Clause 62.2 check is explicitly reported as not satisfied on the available evidence. | F7: Marcus Reed - Contractor Delivery Lead (submission), Planning Manager (record custodian) | G7: Produce the programme alteration relied on by Quotation Rev B and link it to the priced lines by activity and CBS. | H7: 2026-04-02 | I7: Assurance rework target - not a contractual deadline | J7: Open | K7: NEC-05, NEC-10; Clause 64.1 trigger 3; T2, T3
A8: EX-03 | B8: MAJOR - Unverifiable schedule claim | C8: A 10 working-day schedule effect is stated identically in the quotation, forecast, risk and change records and in the controlled event record, but no programme record in the pack measures it. AP12 records variance to accepted finish of 0 for every CE-018 activity at its 2026-02-20 data date. | D8: CE018_Quotation_RevB.csv | QUOT-CE018-REVB | rev B | field schedule_effect_working_days; P6_Activity_Export_AP12.csv | PROG-AP12 | rev AP12 | field variance_to_accepted_finish_working_days | E8: The time element of the assessment is unverified. The GBP 50,000 extended time-related overhead on WSAE-C510 cannot be tested against a revised finish. | F8: Sofia Khan - Project Controls Lead | G8: On receipt of UP13, measure the effect on WSAE-A1200, WSAE-A1300, WSAE-A1400 and milestone WSAE-M9000 and record the measured variance against AP12. | H8: 2026-04-07 | I8: Assurance rework target - not a contractual deadline | J8: Open | K8: T2; NEC-09; Cross-Record Reconciliation time columns
A9: EX-04 | B9: MAJOR - Uncorroborated controlled field | C9: CE018_Event_Record.csv records a full access date of 2026-03-18. No correspondence or programme record in the S2 pack corroborates that date; ACC-004 states only that full access remained subject to operational confirmation. | D9: CE018_Event_Record.csv | CASE-001 | rev 1.1 | field full_access_date; Email_03_Access_Restriction_2026-03-04.eml | ACC-004 | rev 1.0 | E9: A controlled date used in the event record is not traceable to a source record within this scenario pack. | F9: Theo Grant - Access Interface Manager, with Sofia Khan - Project Controls Lead | G9: Supply the access confirmation evidencing the 2026-03-18 full access date, or correct the controlled event record. | H9: 2026-04-07 | I9: Assurance rework target - not a contractual deadline | J9: Open | K9: T1, T2; NEC-02
A10: EX-05 | B10: MINOR - Unverified record statement | C10: QSUB-018 states that the submission links Accepted Programme AP12 and current update UP13. The AP12 link is verifiable; the UP13 link is not, because the record is absent. | D10: Email_06_Quotation_Submission_2026-03-28.eml | QSUB-018 | rev 1.0 | E10: Recorded as a statement made within a project record. It has not been treated as confirmed evidence of the programme alteration. | F10: Marcus Reed - Contractor Delivery Lead | G10: Confirm which controlled programme record was transmitted with the quotation and supply it. | H10: 2026-04-02 | I10: Assurance rework target - not a contractual deadline | J10: Open | K10: NEC-05, NEC-10
A11: EX-06 | B11: MINOR - Control evidence not registered | C11: NEC-01 requires an Early Warning Register reference. No Early Warning Register record is registered in Source_Register.csv rev 3.0 for any scenario, so the item could not be checked. | D11: NEC4_Decision_Readiness_Control_Matrix.csv | CTRL-007 | rev 1.0 | row NEC-01; Source_Register.csv | SRC-001 | rev 3.0 | E11: NEC-01 recorded CONDITIONAL rather than PASSED. Does not prevent review. | F11: Sofia Khan - Project Controls Lead | G11: Register the Early Warning Register reference or record it as out of scope for the demonstration configuration. | H11: 2026-04-15 | I11: Assurance rework target - not a contractual deadline | J11: Open | K11: NEC-01
B13: Critical exceptions | C13: =SUMPRODUCT(--(LEFT(B6:B11,8)="CRITICAL")) -> 2 | D13: EX-01 missing mandatory record; EX-02 Clause 62.2 content not evidenced in the assurance pack.
B14: Total exceptions raised | C14: =COUNTA(A6:A11) -> 6 | D14: 2 critical, 2 major, 2 minor.
A16: B. PENDING ACTIONS
A17: ID | B17: Action | C17: Accountable owner | D17: Due date | E17: Date basis | F17: Status | G17: Dependency | H17: Retest requirement
A18: AC-01 | B18: Supply P6_Activity_Export_UP13.csv rev UP13, or the specific programme alteration relied on by Quotation Rev B | C18: Planning Manager, routed by Sofia Khan | D18: 2026-04-02 | E18: Assurance rework target - not a contractual deadline | F18: Open - required for rework | G18: EX-01, EX-02 | H18: T1, T2, T3; NEC-05, NEC-09, NEC-10, NEC-11; Clause 64.1 triggers 2, 3, 4
A19: AC-02 | B19: Reissue the assurance pack for Project Manager review after the missing record is registered and the retests are complete | C19: Sofia Khan - Project Controls Lead | D19: 2026-04-08 | E19: Assurance rework target - not a contractual deadline | F19: Open - dependent | G19: AC-01 | H19: Full re-run of the Rev 3.0 assessment
A20: AC-03 | B20: Project Manager review of the cited evidence and exceptions (CHG-018 recorded next action) | C20: Elena Brooks - NEC4 Project Manager | D20: 2026-04-02 | E20: Project record date recorded in Change_Register.csv | CHG-018 | rev 5 | F20: Pending - not overdue at cut-off | G20: Change_Register.csv | CHG-018 | rev 5 | field due_date | H20: Not applicable - retained human decision
A21: AC-04 | B21: Project Manager response to Quotation Rev B under configured rule RC-03 | C21: Elena Brooks - NEC4 Project Manager | D21: 2026-04-11 | E21: Configured RC-03 Project Manager response date | F21: Pending - not due at the 2026-03-31 cut-off | G21: Route_Clock_Rules.csv | CTRL-003 | rev 3.0 | row RC-03 | H21: NEC-07 after 2026-04-11
A24: C. ADMINISTRATIVE OBSERVATIONS (non-actionable)
A25: • Source_Register.csv rev 3.0 registers CTRL-001, CTRL-002, CTRL-003, CTRL-005, CTRL-006 and CTRL-007. No CTRL-004 identifier is registered and none is marked required. Numbering gap only; no action required.
A26: • CTRL-002, CTRL-003, CTRL-005, CTRL-007, WBS-001, CBS-001 and XWALK-001 carry no internal revision field. Their revisions are confirmed from the Source Register only.
A27: • Five branding PNG assets and the branding/output-controls note are formatting assets. They are not inventoried, cited, scored or added to the Source Register.

Sheet Decision and Audit Log
A1: DECISION AND AUDIT LOG
A2: Assistant preparation history and the reviewer-entry block reserved to the Project Manager
A4: Date | B4: Entry type | C4: Entry | D4: Actor | E4: Role | F4: Authority | G4: Result / next action | H4: Status | I4: Retest history
A5: 2026-02-24 | B5: Event evidence | C5: Operational access constraint recorded (CORR-001) | D5: Theo Grant | E5: Access Interface Manager | F5: Operational role | G5: Constraint recorded, not a route decision | H5: Closed | I5: n/a
A6: 2026-02-25 | B6: Event evidence | C6: Early warning EW-006 given, separate record from CE-018 | D6: Marcus Reed | E6: Contractor Delivery Lead | F6: Contractor business role | G6: RC-EW satisfied on the configured date | H6: Closed | I6: n/a
A7: 2026-03-04 | B7: Event evidence | C7: Access restriction confirmed (ACC-004); planned AP12 milestone WSAE-A1200 date | D7: Theo Grant | E7: Access Interface Manager | F7: Operational role | G7: RC-00 evidence present; PM determination required | H7: Open - PM | I7: n/a
A8: 2026-03-05 | B8: Contractual record | C8: CE-018 notified to the Project Manager | D8: Marcus Reed | E8: Contractor Delivery Lead | F8: Contractor business role | G8: RC-01 clock started | H8: Closed | I8: n/a
A9: 2026-03-12 | B9: Contractual record | C9: Project Manager response and quotation request (PMR-018) | D9: Elena Brooks | E9: NEC4 Project Manager | F9: Named NEC4 role | G9: RC-01 satisfied; RC-02 clock started | H9: Closed | I9: n/a
A10: 2026-03-28 | B10: Contractual record | C10: Quotation Rev B submitted, GBP 185,000 / 10 working days | D10: Marcus Reed | E10: Contractor Delivery Lead | F10: Contractor business role | G10: RC-02 clock satisfied; content failed NEC-05 and NEC-10 | H10: Open | I10: n/a
A11: 2026-03-31 | B11: Assurance | C11: S2 evidence cut-off applied; assurance assessment run | D11: CE-018 Assurance Assistant | E11: Configured AI support | F11: Non-contractual support | G11: Route: REWORK EVIDENCE PACK. T1=0, T2=0, T3=0, T4=2 | H11: Issued for review | I11: First run - S2
A12: 2026-03-31 | B12: Assurance | C12: Missing mandatory record PROG-UP13 raised as EX-01 | D12: CE-018 Assurance Assistant | E12: Configured AI support | F12: Non-contractual support | G12: Requested from the Planning Manager by 2026-04-02 | H12: Open | I12: Retest T1, T2, T3, NEC-05, NEC-09, NEC-10, NEC-11 and triggers 2-4 on receipt
A13: 2026-04-02 | B13: Pending | C13: CHG-018 recorded next action: review cited evidence and exceptions | D13: Elena Brooks | E13: NEC4 Project Manager | F13: Named NEC4 role | G13: Not yet decided | H13: Pending - not overdue at cut-off | I13: n/a
A14: 2026-04-11 | B14: Pending | C14: RC-03 Project Manager response to Quotation Rev B falls due | D14: Elena Brooks | E14: NEC4 Project Manager | F14: Named NEC4 role | G14: Not made and not anticipated by the assistant | H14: Pending - not due at cut-off | I14: Retest NEC-07 after 2026-04-11
A17: REVIEWER ENTRY BLOCK - reserved to Elena Brooks, NEC4 Project Manager (cells unlocked for entry)
A18: Reviewer name
A19: Review date
A20: Decision status
A21: Directed action
A22: Decision date
A23: Reissue required
A25: The assistant has made no contractual decision and has not drafted any contractual communication. Every entry above is a record of evidence or of assurance preparation.

Sheet Source Citations
A1: SOURCE CITATIONS
A2: Filename, controlled record identifier, revision, locator and evidence purpose
A4: File name | B4: Record ID | C4: Revision | D4: Row / activity / WBS / CBS locator | E4: Evidence purpose
A5: Source_Register.csv | B5: SRC-001 | C5: 3.0 | D5: Row PROG-UP13; full register | E5: Controls the approved evidence inventory; establishes the missing mandatory record
A6: CE018_Control_Brief.txt | B6: CTRL-001 | C6: 3.0 | D6: Permitted task; prohibited actions; retained authority | E6: Assurance method and boundary
A7: Actor_Authority_Matrix.csv | B7: CTRL-002 | C7: 2.1 | D7: Rows TG, MR, SK, EB, AM, AI | E7: Roles, responsibilities and authority boundaries
A8: Route_Clock_Rules.csv | B8: CTRL-003 | C8: 3.0 | D8: Rows RC-EW, RC-00, RC-01, RC-02, RC-03 | E8: Configured triggers, periods, due dates and owners
A9: Four_Test_Checklist.csv | B9: CTRL-005 | C9: 3.0 | D9: Rows T1, T2, T3, T4 | E9: Test purpose, scoring thresholds and failure routes
A10: Expected_Response_Structure.txt | B10: CTRL-006 | C10: 3.0 | D10: Sections 1-11 | E10: Required report, scorecard and JSON structure
A11: NEC4_Decision_Readiness_Control_Matrix.csv | B11: CTRL-007 | C11: 1.0 | D11: Rows NEC-01 to NEC-12 | E11: Configured controls and Clause 64.1 trigger definitions
A12: WBS_Hierarchy.csv | B12: WBS-001 | C12: 1.0 | D12: Rows WSAE.10, WSAE.20.10, WSAE.30.10, WSAE.30.20 | E12: Confirms every crosswalk WBS identifier exists
A13: CBS_Hierarchy.csv | B13: CBS-001 | C13: 1.0 | D13: Rows WSAE-C210, C310, C320, C510, C610 | E13: Confirms every crosswalk CBS account exists
A14: CE018_WBS_Programme_CBS_Crosswalk.csv | B14: XWALK-001 | C14: 1.0 | D14: 5 CE-018 rows; row 5 WSAE-M9000 | E14: Event to WBS, activity and CBS linkage
A15: CE018_Event_Record.csv | B15: CASE-001 | C15: 1.1 | D15: Fields planned_access_date, restricted_access_date, full_access_date, schedule_effect_working_days, commercial_exposure_gbp, assessment_cutoff | E15: Controlled event facts and cut-off
... A27: Change_Register.csv | B27: CHG-018 | C27: 5 | D27: Row CHG-018; due date 2026-04-02; decision status not yet decided | E27: Change status, owner and next action
