Workbook

Sheet Executive Dashboard
A1: CE-018 PROJECT CONTROLS ASSURANCE — EXECUTIVE DASHBOARD
A2: Westbridge Station Access and Enabling Works (WSAE) — CE-018: Restricted access to the Platform 4 worksite — Rev 3.0 — FICTIONAL DEMONSTRATION DATA
A5: Project | B5: Westbridge Station Access and Enabling Works (WSAE)
A6: Client | B6: Westbridge Transit Authority
A7: Contractor | B7: Northstar Civil Engineering Ltd
A8: Interface organisation | B8: CityRail Operations
A9: Event | B9: CE-018 — Restricted access to the Platform 4 worksite
A10: Related early warning | B10: EW-006 — separate earlier warning concerning the same access issue
A11: Scenario | B11: S1 — NEC4 ECC demonstration
A12: Assessment cut-off | B12: 2026-03-31
A13: Decision owner | B13: Elena Brooks — NEC4 Project Manager
A14: Control owner | B14: Sofia Khan — Project Controls Lead
A15: Classification | B15: Fictional Demonstration Data
A16: Report status / revision | B16: ISSUED FOR PROJECT MANAGER REVIEW (IFR) — NOT APPROVED — Rev 3.0
A18: FOUR-TEST TILES
A19: Test | B19: Test name | C19: Score | D19: Status | E19: Critical Failure? | F19: Owner
A20: T1 | B20: Evidence and version | C20: ='Four-Test Scorecard'!C6 -> 2 | D20: ='Four-Test Scorecard'!D6 -> PASS | E20: =IF('Four-Test Scorecard'!G6="Yes","YES","No") -> No | F20: Sofia Khan
A21: T2 | B21: Records agree | C21: ='Four-Test Scorecard'!C7 -> 2 | D21: ='Four-Test Scorecard'!D7 -> PASS | E21: =IF('Four-Test Scorecard'!G7="Yes","YES","No") -> No | F21: Sofia Khan
A22: T3 | B22: Configured NEC4 route and clock | C22: ='Four-Test Scorecard'!C8 -> 1 | D22: ='Four-Test Scorecard'!D8 -> BOUNDED LIMITATION | E22: =IF('Four-Test Scorecard'!G8="Yes","YES","No") -> No | F22: Elena Brooks (judgement) / Sofia Khan (evidence compilation)
A23: T4 | B23: Human authority | C23: ='Four-Test Scorecard'!C9 -> 2 | D23: ='Four-Test Scorecard'!D9 -> PASS | E23: =IF('Four-Test Scorecard'!G9="Yes","YES","No") -> No | F23: Sofia Khan
A25: Total score (of 8) | B25: =SUM(C20:C23) -> 7
A26: Critical-failure count | B26: =SUMPRODUCT(--(C20:C23=0)) -> 0
A27: Recommended route | B27: =IF(B26>0,"CRITICAL FAILURE — SEE ROUTING RULES",IF(COUNTIF(C20:C23,1)>0,"READY WITH CONDITIONS","READY FOR PROJECT MANAGER REVIEW")) -> READY WITH CONDITIONS
A28: Schedule effect (working days) | B28: 10
A29: Commercial exposure (GBP) | B29: 185000
A30: Configured NEC4 process-assurance result | B30: CONFIGURED NEC4 PROCESS CONTROLS SATISFIED WITH CONDITIONS
A31: Next action / next due date | B31: ACT-01 — Project Manager response to Quotation Rev B, due 2026-04-11 (Elena Brooks)
A33: FICTIONAL DEMONSTRATION DATA — Not a contractual assessment or communication. Elena Brooks, NEC4 Project Manager, retains the contractual decision.

Sheet Evidence Register
A1: EVIDENCE REGISTER
A2: Westbridge Station Access and Enabling Works (WSAE) — CE-018: Restricted access to the Platform 4 worksite — Rev 3.0 — FICTIONAL DEMONSTRATION DATA
A5: Required? | B5: Present? | C5: Filename | D5: Record ID | E5: Type | F5: Revision | G5: Evidence Owner / Custodian | H5: Intended Use | I5: Citation Reference
A6: Yes | B6: Yes | C6: Source_Register.csv | D6: SRC-001 | E6: Project Context | F6: 3.0 | G6: Project Controls Lead | H6: Source register | I6: Source_Register.csv (SRC-001) rev 3.0
A7: Yes | B7: Yes | C7: CE018_Control_Brief.txt | D7: CTRL-001 | E7: Project Context | F7: 3.0 | G7: Project Controls Lead | H7: Control brief | I7: CE018_Control_Brief.txt (CTRL-001) rev 3.0
A8: Yes | B8: Yes | C8: Actor_Authority_Matrix.csv | D8: CTRL-002 | E8: Project Context | F8: 2.1 | G8: Project Controls Lead | H8: Authority matrix | I8: Actor_Authority_Matrix.csv (CTRL-002) rev 2.1
A9: Yes | B9: Yes | C9: Route_Clock_Rules.csv | D9: CTRL-003 | E9: Project Context | F9: 3.0 | G9: Project Controls Lead | H9: Route and clock rules | I9: Route_Clock_Rules.csv (CTRL-003) rev 3.0
A10: Yes | B10: Yes | C10: Four_Test_Checklist.csv | D10: CTRL-005 | E10: Project Context | F10: 3.0 | G10: Project Controls Lead | H10: Assurance checklist | I10: Four_Test_Checklist.csv (CTRL-005) rev 3.0
A11: Yes | B11: Yes | C11: Expected_Response_Structure.txt | D11: CTRL-006 | E11: Project Context | F11: 3.0 | G11: Project Controls Lead | H11: Response structure | I11: Expected_Response_Structure.txt (CTRL-006) rev 3.0
A12: Yes | B12: Yes | C12: NEC4_Decision_Readiness_Control_Matrix.csv | D12: CTRL-007 | E12: Project Context | F12: 1.0 | G12: Project Controls Lead | H12: NEC4 control matrix | I12: NEC4_Decision_Readiness_Control_Matrix.csv (CTRL-007) rev 1.0
A13: Yes | B13: Yes | C13: WBS_Hierarchy.csv | D13: WBS-001 | E13: Project Context | F13: 1.0 | G13: Project Controls Lead | H13: WBS | I13: WBS_Hierarchy.csv (WBS-001) rev 1.0
A14: Yes | B14: Yes | C14: CBS_Hierarchy.csv | D14: CBS-001 | E14: Project Context | F14: 1.0 | G14: Project Controls Lead | H14: CBS | I14: CBS_Hierarchy.csv (CBS-001) rev 1.0
A15: Yes | B15: Yes | C15: CE018_WBS_Programme_CBS_Crosswalk.csv | D15: XWALK-001 | E15: Project Context | F15: 1.0 | G15: Project Controls Lead | H15: Crosswalk | I15: CE018_WBS_Programme_CBS_Crosswalk.csv (XWALK-001) rev 1.0
A16: Yes | B16: Yes | C16: CE018_Event_Record.csv | D16: CASE-001 | E16: Project Context | F16: 1.1 | G16: Project Controls Lead | H16: Event record | I16: CE018_Event_Record.csv (CASE-001) rev 1.1
... A30: No (S3 only) | B30: No — correctly absent | C30: Risk_Register_CONFLICT.csv | D30: RISK-044-X | E30: Other-scenario conflict file | F30: — | G30: — | H30: Not registered as S1 evidence; correctly absent from the S1 evidence pack | I30: Risk_Register_CONFLICT.csv
A32: Five formatting-only image assets (organisation marks and the Fictional Demonstration Data badge) were supplied for layout purposes only and are excluded from the evidence inventory, citations and scoring per the run instruction.

Sheet Cross-Record Reconciliation
A1: CROSS-RECORD RECONCILIATION — AP12 / UP13 / QUOTATION / FORECAST / RISK / CHANGE
A2: Westbridge Station Access and Enabling Works (WSAE) — CE-018: Restricted access to the Platform 4 worksite — Rev 3.0 — FICTIONAL DEMONSTRATION DATA
A5: WBS | B5: Activity | C5: CBS | D5: Cost Element | E5: AP12 Position | F5: UP13 Position | G5: Quotation (GBP) | H5: Forecast (GBP) | I5: Risk (GBP) | J5: Change (GBP) | K5: Variance / Note
A6: WSAE.20.10 | B6: WSAE-A1200 | C6: WSAE-C210 | D6: Access / Possession Standby | E6: Planned start/finish 04 Mar 2026 (0 days duration, milestone) | F6: Actual finish 18 Mar 2026 — 10 working days later than AP12 | G6: 25000 | H6: 25000 | I6: — | J6: — | K6: Quotation = Forecast. Risk and Change records carry the event total, not a per-CBS split.
A7: WSAE.30.10 | B7: WSAE-A1300 | C7: WSAE-C310 | D7: Direct Labour | E7: Planned 05–18 Mar 2026 (10 days) | F7: Actual start 19 Mar 2026, in progress, early finish forecast 01 Apr 2026 — 10-day slip | G7: 55000 | H7: 55000 | I7: — | J7: — | K7: Quotation = Forecast.
A8: WSAE.30.10 | B8: WSAE-A1300 | C8: WSAE-C320 | D8: Plant and Equipment | E8: Planned 05–18 Mar 2026 (10 days) | F8: As above — 10-day slip | G8: 35000 | H8: 35000 | I8: — | J8: — | K8: Quotation = Forecast.
A9: WSAE.30.20 | B9: WSAE-A1400 | C9: WSAE-C510 | D9: Time-Related Overheads | E9: Planned 19–27 Mar 2026 (7 days) | F9: Forecast start 02 Apr 2026, forecast finish 14 Apr 2026 — 10-day slip | G9: 50000 | H9: 50000 | I9: — | J9: — | K9: Quotation = Forecast.
A10: WSAE.10 | B10: WSAE-M9000 | C10: WSAE-C610 | D10: CE-018 Risk Allowance | E10: Planned finish milestone 27 Mar 2026 | F10: Forecast finish 14 Apr 2026 — 10-day slip | G10: 20000 | H10: 20000 | I10: — | J10: — | K10: Quotation = Forecast.
A11: WSAE.20.10 (event total) | B11: — | C11: — | D11: Event total (Risk Register / Change Register) | E11: n/a | F11: 10 working days (matches quotation total) | G11: 185000 | H11: 185000 | I11: 185000 | J11: 185000 | K11: All five records agree at GBP 185,000 / 10 working days. No material conflict identified.
D12: Line-item subtotal (Quotation = Forecast) | G12: =SUM(G6:G10) -> 185000 | H12: =SUM(H6:H10) -> 185000
A14: No material conflict identified across Quotation Rev B, Cost Forecast P07, Risk Register RISK-044 and Change Register CHG-018. All figures reconcile at GBP 185,000 / 10 working days. Do not average conflicting values — none were found in this scenario.

Sheet Four-Test Scorecard
A1: FOUR-TEST SCORECARD
A2: Westbridge Station Access and Enabling Works (WSAE) — CE-018: Restricted access to the Platform 4 worksite — Rev 3.0 — FICTIONAL DEMONSTRATION DATA
A5: Test | B5: Purpose | C5: Score (0-2) | D5: Status | E5: Finding | F5: Source Citation | G5: Critical Failure? | H5: Consequence | I5: Owner
A6: T1 | B6: Evidence and version | C6: 2 | D6: =IF(C6=2,"PASS",IF(C6=1,"BOUNDED LIMITATION","CRITICAL FAILURE")) -> PASS | E6: All 11 registered Project Context files and all 12 registered S1 evidence files are present at the approved revision in Source_Register.csv, and no S2/S3/S4 replacement or conflict file is present in the evidence pack. | F6: Source_Register.csv (SRC-001) rev 3.0; all 12 S1 evidence file headers | G6: No | H6: None — evidence base is controlled and complete for S1. | I6: Sofia Khan
A7: T2 | B7: Records agree | C7: 2 | D7: =IF(C7=2,"PASS",IF(C7=1,"BOUNDED LIMITATION","CRITICAL FAILURE")) -> PASS | E7: Quotation Rev B, Cost Forecast P07, Risk Register RISK-044 and Change Register CHG-018 all state 10 working days and GBP 185,000, and reconcile to the same WBS, activity and CBS references. UP13 variance_to_accepted_finish_working_days confirms the 10-day slip against AP12. | F7: CE018_Quotation_RevB.csv (QUOT-CE018-REVB); Cost_Forecast_P07.csv (FCST-P07); Risk_Register.csv (RISK-044); Change_Register.csv (CHG-018); P6_Activity_Export_UP13.csv (PROG-UP13) | G7: No | H7: None — no material conflict identified in the evidence supplied. | I7: Sofia Khan
A8: T3 | B8: Configured NEC4 route and clock | C8: 1 | D8: =IF(C8=2,"PASS",IF(C8=1,"BOUNDED LIMITATION","CRITICAL FAILURE")) -> BOUNDED LIMITATION | E8: All objective route/clock dates in Route_Clock_Rules.csv are met or correctly pending-not-due (RC-EW, RC-00, RC-01, RC-02 complete; RC-03 due 11 April 2026, not overdue at the 31 March 2026 cut-off). However rule RC-02 is itself annotated ‘content still subject to NEC-05/NEC-10’: UP13 is linked to the quotation and shows the ten-working-day effect, but the evidence does not establish whether it constitutes the Clause 62.2 alterations to the Accepted Programme. This is a bounded, clearly owned limitation, not a missing record, overdue clock or unresolved Clause 64.1 trigger. | F8: Route_Clock_Rules.csv rules RC-EW, RC-00, RC-01, RC-02, RC-03; NEC4_Decision_Readiness_Control_Matrix.csv controls NEC-01, NEC-05, NEC-10 | G8: No | H8: Bounded — does not block Project Manager review but should be confirmed before the RC-03 due date. | I8: Elena Brooks (judgement) / Sofia Khan (evidence compilation)
A9: T4 | B9: Human authority | C9: 2 | D9: =IF(C9=2,"PASS",IF(C9=1,"BOUNDED LIMITATION","CRITICAL FAILURE")) -> PASS | E9: Every evidence record and the requested output confirm that notification, quotation, review and decision actions sit with the named actors in Actor_Authority_Matrix.csv; the assistant has prepared cited evidence-status material only and has not notified, instructed, assessed, accepted or implemented CE-018. | F9: Actor_Authority_Matrix.csv (CTRL-002); Email_05_PM_Response_2026-03-12.eml (PMR-018); Change_Register.csv (CHG-018) decision_owner field | G9: No | H9: None. | I9: Sofia Khan
B10: TOTAL | C10: =SUM(C6:C9) -> 7
B11: Critical-failure count | C11: =SUMPRODUCT(--(C6:C9=0)) -> 0
B12: Any score of 0 determines the route irrespective of the total score.

Sheet NEC4 Control Cross-Reference
A1: NEC4 DECISION-READINESS CONTROL RESULTS
A2: Westbridge Station Access and Enabling Works (WSAE) — CE-018: Restricted access to the Platform 4 worksite — Rev 3.0 — FICTIONAL DEMONSTRATION DATA
A5: Control ID | B5: Control Group | C5: NEC4 Clause | D5: Four-Test Link | E5: Decision-Readiness Question | F5: Result | G5: Finding | H5: Citation | I5: Owner
A6: NEC-01 | B6: Early warning | C6: 15.1 | D6: T1/T3 | E6: Is there dated evidence that the access risk was warned when it became apparent? | F6: CONDITIONAL | G6: Dated evidence exists: initial risk email 24 Feb 2026, EW-006 recorded 25 Feb 2026 — one working day later. RC-EW criticality is Major (not Critical). Whether one day meets ‘as soon as practicable’ is a human contractual judgement per the Route_Clock_Rules basis note. | H6: Email_01_Access_Risk_2026-02-24.eml (CORR-001); Email_02_EW006_2026-02-25.eml (EW-006); Route_Clock_Rules.csv rule RC-EW | I6: Elena Brooks
A7: NEC-02 | B7: Access and event basis | C7: 33.1 / 60.1(2) | D7: T1/T3 | E7: Do the Accepted Programme and access record evidence the planned access date and the actual restriction? | F7: EVIDENCED_PM_DETERMINATION | G7: AP12 shows planned access 04 Mar 2026 (activity WSAE-A1200); ACC-004 confirms only a 2-hour escorted window was available against the planned 8-hour window. Evidence is present and consistent; whether this constitutes a compensation event is reserved to the Project Manager. | H7: P6_Activity_Export_AP12.csv (PROG-AP12); Email_03_Access_Restriction_2026-03-04.eml (ACC-004) | I7: Elena Brooks
A8: NEC-03 | B8: Contractor notification | C8: 61.3 | D8: T1/T3 | E8: Was the Contractor notification separately recorded, correctly routed and within the configured time-bar control? | F8: PASSED | G8: CE-018 notification (05 Mar 2026) is a distinct record from EW-006, addressed to Elena Brooks and copied to Sofia Khan, one day after the access restriction was confirmed. Route_Clock_Rules.csv does not configure a distinct Clause 61.3 time-bar period for this demonstration (administrative observation, not a critical gap given the short elapsed time). | H8: Email_04_CE018_Notification_2026-03-05.eml (CE-018 email); Source_Register.csv (SRC-001) | I8: Sofia Khan
A9: NEC-04 | B9: PM notification response | C9: 61.4 | D9: T3 | E9: Did the Project Manager respond within the configured one-week period? | F9: PASSED | G9: RC-01: trigger 05 Mar 2026, due 12 Mar 2026 (1 week), actual response 12 Mar 2026 — on the configured due date. | H9: Route_Clock_Rules.csv rule RC-01; Email_05_PM_Response_2026-03-12.eml (PMR-018) | I9: Elena Brooks
A10: NEC-05 | B10: Quotation content | C10: 62.2 | D10: T1/T2/T3 | E10: Does the quotation pack contain assessment details and, where remaining work is altered, the required alterations to the Accepted Programme? | F10: PM_JUDGEMENT | G10: Assessment details (cost build-up by CBS account, 10-day schedule effect) are present and reconcile with the Forecast, Risk Register and Change Register. UP13 is linked to the quotation and shows the ten-working-day effect; however, the evidence does not establish whether it constitutes the Clause 62.2 alterations to the Accepted Programme. Whether UP13 satisfies the Clause 62.2 requirement is reserved to the Project Manager. | H10: CE018_Quotation_RevB.csv (QUOT-CE018-REVB); Email_06_Quotation_Submission_2026-03-28.eml (QSUB-018); P6_Activity_Export_UP13.csv (PROG-UP13) | I10: Elena Brooks
A11: NEC-06 | B11: Quotation submission clock | C11: 62.3 | D11: T3 | E11: Was the quotation and assessment detail submitted within the configured three-week period? | F11: PASSED | G11: RC-02: trigger (PM request) 12 Mar 2026, due 02 Apr 2026 (21 days), actual submission 28 Mar 2026 — within the configured period. | H11: Route_Clock_Rules.csv rule RC-02; Email_06_Quotation_Submission_2026-03-28.eml (QSUB-018) | I11: Marcus Reed
A12: NEC-07 | B12: PM quotation response | C12: 62.3 / 62.6 | D12: T3/T4 | E12: Is the Project Manager response recorded, or correctly classified as pending-not-due at the cut-off? | F12: PENDING_NOT_DUE | G12: RC-03: trigger 28 Mar 2026, due 11 Apr 2026 (14 days). No decision record exists at the 31 Mar 2026 cut-off; Change_Register.csv confirms decision_status = ‘Not yet decided’. Correctly pending, not overdue. | H12: Route_Clock_Rules.csv rule RC-03; Change_Register.csv (CHG-018) | I12: Elena Brooks
A13: NEC-08 | B13: Clause 64.1 trigger 1 — late/missing quotation | C13: 64.1 | D13: T2/T3 | E13: Has the Contractor failed to submit the quotation and assessment details within the permitted time? | F13: NOT_TRIGGERED | G13: Quotation Rev B was submitted 28 Mar 2026, within the RC-02 due date of 02 Apr 2026. | H13: Route_Clock_Rules.csv rule RC-02; Email_06_Quotation_Submission_2026-03-28.eml (QSUB-018) | I13: Sofia Khan
A14: NEC-09 | B14: Clause 64.1 trigger 2 — incorrect assessment | C14: 64.1 | D14: T2/T3 | E14: Is there a material inconsistency or unsupported basis that may indicate the Contractor's assessment is not correct? | F14: PM_JUDGEMENT | G14: NO EVIDENCE DEFECT IDENTIFIED: Quotation, Forecast P07, Risk Register and Change Register agree on schedule effect (10 days) and cost (GBP 185,000) with consistent WBS/CBS citations; no unsupported or irreconcilable basis was identified in the evidence supplied. Contractual status: PROJECT MANAGER JUDGEMENT — the assistant does not decide whether the Contractor's assessment is contractually correct; that determination is reserved to Elena Brooks. | H14: CE018_Quotation_RevB.csv (QUOT-CE018-REVB); Cost_Forecast_P07.csv (FCST-P07); Risk_Register.csv (RISK-044); Change_Register.csv (CHG-018) | I14: Elena Brooks (final judgement)
A15: NEC-10 | B15: Clause 64.1 trigger 3 — programme alteration missing | C15: 62.2 / 64.1 | D15: T1/T2/T3 | E15: Where the event alters remaining work, was the required programme or alteration submitted with the quotation pack? | F15: PM_JUDGEMENT | G15: UP13 is present and is explicitly linked in the quotation submission email, showing the ten-working-day effect; however, the evidence does not establish whether it constitutes the Clause 62.2 alterations to the Accepted Programme. NEC guidance confirms that programme alterations must accompany a quotation where remaining work is affected, and their absence may require a Project Manager assessment (see Official Reference URL). This is carried as a PM-judgement item under Exception EXC-01. | H15: Email_06_Quotation_Submission_2026-03-28.eml (QSUB-018); P6_Activity_Export_UP13.csv (PROG-UP13) | I15: Elena Brooks
A16: NEC-11 | B16: Clause 64.1 trigger 4 — latest programme not accepted | C16: 31.1 / 31.3 / 32.2 / 64.1 | D16: T1/T3 | E16: Is an Accepted Programme available and is any relevant non-acceptance status identified? | F16: NOT_TRIGGERED | G16: AP12 is registered and confirmed as the Accepted Programme (Source_Register.csv; CE018_Event_Record.csv field accepted_programme). No Project Manager non-acceptance record for any later programme submission is present in the evidence pack. | H16: P6_Activity_Export_AP12.csv (PROG-AP12); Source_Register.csv (SRC-001); CE018_Event_Record.csv (CASE-001) | I16: Sofia Khan
A17: NEC-12 | B17: Retained human authority | C17: Clauses 61–64 and Authority Matrix | D17: T4 | E17: Are the remaining notification, assessment, acceptance, instruction and implementation actions reserved to the named NEC4 role? | F17: PASSED | G17: All evidence and prepared outputs confirm Elena Brooks retains the decision. The assistant has not notified, instructed, assessed, accepted or implemented CE-018 at any point in this assessment. | H17: Actor_Authority_Matrix.csv (CTRL-002); Change_Register.csv (CHG-018) | I17: Elena Brooks

Sheet Clause 64.1 Triggers
A1: CLAUSE 64.1 INTERVENTION TRIGGERS
A2: Westbridge Station Access and Enabling Works (WSAE) — CE-018: Restricted access to the Platform 4 worksite — Rev 3.0 — FICTIONAL DEMONSTRATION DATA
A5: Trigger | B5: Evidence Finding | C5: Contractual Status | D5: Basis
A6: Trigger 1 — Late or missing quotation (NEC-08) | B6: Quotation submitted 28 Mar 2026, within the RC-02 due date of 02 Apr 2026. | C6: NOT_TRIGGERED | D6: Quotation submitted 28 Mar 2026, within the RC-02 due date of 02 Apr 2026.
A7: Trigger 2 — Incorrect assessment (NEC-09) | B7: NO EVIDENCE DEFECT IDENTIFIED — cross-record reconciliation shows no unsupported or irreconcilable time/cost position in the evidence supplied. | C7: PROJECT MANAGER JUDGEMENT | D7: Contractual correctness of the Contractor's assessment is not decided by the assistant; that determination is reserved to Elena Brooks.
A8: Trigger 3 — Programme alteration missing (NEC-10) | B8: UP13 is present and linked to the quotation submission, showing the ten-working-day effect. | C8: PROJECT MANAGER JUDGEMENT | D8: The evidence does not establish whether UP13 constitutes the Clause 62.2 alterations to the Accepted Programme (see NEC-05 / EXC-01). NEC guidance confirms programme alterations must accompany a quotation where remaining work is affected, and their absence may require a Project Manager assessment.
A9: Trigger 4 — Latest programme not accepted (NEC-11) | B9: AP12 is confirmed as the Accepted Programme; no non-acceptance record for a later programme submission is present. | C9: NOT_TRIGGERED | D9: AP12 is confirmed as the Accepted Programme; no non-acceptance record for a later programme submission is present.
A11: Summary: No Clause 64.1 trigger is evidenced as definitively activated. Triggers 2 and 3 remain subject to Project Manager judgement.
A12: The assistant does not decide whether the Contractor's assessment is contractually correct.
A13: NEC guidance: programme alterations must accompany a quotation where remaining work is affected, and their absence may require a Project Manager assessment. See NEC guidance on compensation-event assessments: https://www.neccontract.com/news/when-and-why-nec-project-managers-have-to-assess-compensation-events

Sheet Exceptions and Actions
A1: EXCEPTIONS, ADMINISTRATIVE OBSERVATIONS AND ACTIONS
A2: Westbridge Station Access and Enabling Works (WSAE) — CE-018: Restricted access to the Platform 4 worksite — Rev 3.0 — FICTIONAL DEMONSTRATION DATA
A5: ID | B5: Category / Classification | C5: Issue / Description | D5: Consequence | E5: Evidence | F5: Accountable Owner | G5: Due Date | H5: Action Status | I5: Retest Requirement
A6: ASSURANCE EXCEPTIONS
A7: EXC-01 | B7: Quotation content / programme alteration (NEC-05, NEC-10, T3) | C7: UP13 is linked to the quotation and shows the ten-working-day effect; however, the evidence does not establish whether it constitutes the Clause 62.2 alterations to the Accepted Programme. | D7: Bounded — does not prevent Project Manager review but should be confirmed before the RC-03 response is issued. | E7: Email_06_Quotation_Submission_2026-03-28.eml (QSUB-018); P6_Activity_Export_UP13.csv (PROG-UP13) | F7: Elena Brooks (judgement) / Sofia Khan (evidence compilation) | G7: 2026-04-11 (aligned to RC-03 due date) | H7: Open | I7: Re-run NEC-05, NEC-10 and T3 once the Project Manager confirms the position, or by the RC-03 due date if earlier.
A9: ADMINISTRATIVE OBSERVATIONS (non-actionable, informational only)
A10: AO-01 | B10: Early warning EW-006 was recorded one working day after the initial risk email (24→25 Feb 2026). RC-EW criticality is Major, not Critical; the basis note reserves the promptness judgement to the Project Manager. | G10: Route_Clock_Rules.csv rule RC-EW
A11: AO-02 | B11: Route_Clock_Rules.csv does not configure a distinct Clause 61.3 notification time-bar period for this demonstration. The CE-018 notification (05 Mar) followed the access restriction confirmation (04 Mar) by one day, well inside any customary period. | G11: Route_Clock_Rules.csv; Email_04_CE018_Notification_2026-03-05.eml (CE-018 email)
A12: AO-03 | B12: UP13's data date (20 Mar 2026) precedes the Quotation Rev B submission date (28 Mar 2026) by 8 days. It is the most recent controlled update in the S1 evidence pack. | G12: P6_Activity_Export_UP13.csv (PROG-UP13)
A14: PENDING ACTIONS
A15: ACT-01 | B15: Pending clock — not overdue | C15: Project Manager response to Quotation Rev B | D15: Not overdue at cut-off | E15: Confirmation of EXC-01 recommended before response is issued | F15: Elena Brooks | G15: 2026-04-11 | H15: Pending | I15: Re-run T3 and NEC-07 at or after the due date.
A16: ACT-02 | B16: Pending decision — not overdue | C16: Change Register CHG-018 decision — currently ‘Not yet decided’ | D16: Not overdue at cut-off | E16: None outstanding | F16: Elena Brooks | G16: 2026-04-02 | H16: Pending | I16: Update Change Register on decision; re-run T2 cross-record reconciliation if the decision alters cost or schedule figures.

Sheet Decision and Audit Log
A1: DECISION AND AUDIT LOG
A2: Westbridge Station Access and Enabling Works (WSAE) — CE-018: Restricted access to the Platform 4 worksite — Rev 3.0 — FICTIONAL DEMONSTRATION DATA
A5: Assessment Date | B5: Evidence Cut-off | C5: Route | D5: Reviewer | E5: Decision Status | F5: Decision Date | G5: Action | H5: Approval | I5: Retest History
A6: 2026-08-22 | B6: 2026-03-31 | C6: READY WITH CONDITIONS | D6: CE-018 Project Controls Assurance Assistant | E6: Prepared — awaiting Project Manager review | F6: — | G6: Issue Rev 3.0 assurance pack (Report, Scorecard, JSON) to Elena Brooks | H6: Pending — EB | I6: Initial S1 Rev 3.0 run — no prior scores carried forward
A8: This log records the assurance preparation step only. The Project Manager's own review, decision and approval must be recorded by Elena Brooks and are not entered by the assistant.

Sheet Source Citations
A1: SOURCE CITATIONS
A2: Westbridge Station Access and Enabling Works (WSAE) — CE-018: Restricted access to the Platform 4 worksite — Rev 3.0 — FICTIONAL DEMONSTRATION DATA
A5: Filename | B5: Record ID | C5: Revision | D5: Row / Activity / WBS / CBS Locator | E5: Evidence Purpose
A6: Source_Register.csv | B6: SRC-001 | C6: 3.0 | D6: Whole file — controls approved evidence pack | E6: Source register
A7: CE018_Control_Brief.txt | B7: CTRL-001 | C7: 3.0 | D7: Whole file — permitted task, method, prohibited actions | E7: Control brief
A8: Actor_Authority_Matrix.csv | B8: CTRL-002 | C8: 2.1 | D8: Rows TG, MR, SK, EB, AM, AI | E8: Authority matrix
A9: Route_Clock_Rules.csv | B9: CTRL-003 | C9: 3.0 | D9: Rows RC-EW, RC-00, RC-01, RC-02, RC-03 | E9: Route and clock rules
A10: Four_Test_Checklist.csv | B10: CTRL-005 | C10: 3.0 | D10: Rows T1, T2, T3, T4 | E10: Assurance checklist
A11: Expected_Response_Structure.txt | B11: CTRL-006 | C11: 3.0 | D11: Whole file — required response structure | E11: Response structure
A12: NEC4_Decision_Readiness_Control_Matrix.csv | B12: CTRL-007 | C12: 1.0 | D12: Rows NEC-01 to NEC-12 | E12: NEC4 control matrix
A13: WBS_Hierarchy.csv | B13: WBS-001 | C13: 1.0 | D13: Rows WSAE.10, WSAE.20.10, WSAE.30.10, WSAE.30.20 | E13: WBS
A14: CBS_Hierarchy.csv | B14: CBS-001 | C14: 1.0 | D14: Rows WSAE-C210, C310, C320, C510, C610 | E14: CBS
A15: CE018_WBS_Programme_CBS_Crosswalk.csv | B15: XWALK-001 | C15: 1.0 | D15: All 5 rows — CE-018 WBS/Activity/CBS links | E15: Crosswalk
A16: CE018_Event_Record.csv | B16: CASE-001 | C16: 1.1 | D16: Single row — CE-018 controlled facts | E16: Event record
... A28: Change_Register.csv | B28: CHG-018 | C28: 5 | D28: Single row — CHG-018 | E28: Status, owner, next action and expected effect
